sherpa_onnx/__main__.py
sherpa_onnx/_info.py
sherpa_onnx/include/sherpa-onnx/c-api/c-api.h
sherpa_onnx/include/sherpa-onnx/c-api/cxx-api.h
sherpa_onnx/lib/libonnxruntime.so
sherpa_onnx/lib/libsherpa-onnx-c-api.so
sherpa_onnx/lib/libsherpa-onnx-cxx-api.so
sherpa_onnx_core-1.12.23.dist-info/METADATA
sherpa_onnx_core-1.12.23.dist-info/WHEEL
sherpa_onnx_core-1.12.23.dist-info/top_level.txt
sherpa_onnx_core-1.12.23.dist-info/RECORD
